COPYING
MANIFEST.in
README.rst
buildout.cfg
pyproject.toml
requirements.txt
setup.py
version.txt
beat/__init__.py
beat.editor.egg-info/PKG-INFO
beat.editor.egg-info/SOURCES.txt
beat.editor.egg-info/dependency_links.txt
beat.editor.egg-info/entry_points.txt
beat.editor.egg-info/not-zip-safe
beat.editor.egg-info/requires.txt
beat.editor.egg-info/top_level.txt
beat/editor/__init__.py
beat/editor/decorators.py
beat/editor/resources.py
beat/editor/utils.py
beat/editor/version.py
beat/editor/backend/__init__.py
beat/editor/backend/asset.py
beat/editor/backend/assetmodel.py
beat/editor/backend/delegates.py
beat/editor/backend/eventfilters.py
beat/editor/backend/experimentmodel.py
beat/editor/backend/resourcemodels.py
beat/editor/scripts/__init__.py
beat/editor/scripts/editor_cli.py
beat/editor/test/__init__.py
beat/editor/test/conftest.py
beat/editor/test/test_algorithmeditor.py
beat/editor/test/test_asset.py
beat/editor/test/test_assetbrowser.py
beat/editor/test/test_assetmodel.py
beat/editor/test/test_assetwidget.py
beat/editor/test/test_databaseeditor.py
beat/editor/test/test_dataformateditor.py
beat/editor/test/test_decorators.py
beat/editor/test/test_delegates.py
beat/editor/test/test_dialogs.py
beat/editor/test/test_editors.py
beat/editor/test/test_experimenteditor.py
beat/editor/test/test_experimentmodel.py
beat/editor/test/test_libraries.py
beat/editor/test/test_libraryeditor.py
beat/editor/test/test_parameterwidget.py
beat/editor/test/test_plottereditor.py
beat/editor/test/test_plotterparameterseditor.py
beat/editor/test/test_protocoletemplateditor.py
beat/editor/test/test_resourcemodels.py
beat/editor/test/test_scrollwidget.py
beat/editor/test/test_spinboxes.py
beat/editor/test/test_toolchaineditor.py
beat/editor/test/test_utils.py
beat/editor/widgets/__init__.py
beat/editor/widgets/algorithmeditor.py
beat/editor/widgets/assetbrowser.py
beat/editor/widgets/assetwidget.py
beat/editor/widgets/databaseeditor.py
beat/editor/widgets/dataformateditor.py
beat/editor/widgets/dialogs.py
beat/editor/widgets/editor.py
beat/editor/widgets/experimenteditor.py
beat/editor/widgets/field.py
beat/editor/widgets/libraries.py
beat/editor/widgets/libraryeditor.py
beat/editor/widgets/mainwindow.py
