Metadata-Version: 2.1
Name: beat.editor
Version: 2.0.4
Summary: Local editor for BEAT objects
Home-page: https://gitlab.idiap.ch/beat/beat.editor
Author: Idiap Research Institute
Author-email: beat.support@idiap.ch
License: GPLv3
Classifier: Framework :: BEAT
Classifier: Development Status :: 5 - Production/Stable
Classifier: Intended Audience :: Developers
Classifier: License :: OSI Approved :: GNU General Public License v3 (GPLv3)
Classifier: Natural Language :: English
Classifier: Programming Language :: Python
Classifier: Programming Language :: Python :: 3
Classifier: Topic :: Software Development :: Libraries :: Python Modules
License-File: COPYING
